{
  "__note__": "This is file is autogenerated, do not edit it manually. For more info https://data.aoe4world.com/",
  "__version__": "0.0.2",
  "id": "granary",
  "name": "Granary",
  "type": "building",
  "civs": [
    "ch",
    "zx"
  ],
  "unique": true,
  "displayClasses": [
    "Economy Building"
  ],
  "classes": [
    "building",
    "economy_building",
    "granary",
    "gristmill",
    "land_food_deposit_4_by_4",
    "mill",
    "resource_drop_off",
    "siegeable"
  ],
  "minAge": 1,
  "icon": "https://data.aoe4world.com/images/buildings/granary-1.png",
  "description": "Villagers can drop off Food at this building. Improves the Farm gather rate of nearby Villagers by +10% (stacks with other Granaries). Generates tax each time a resource is dropped off.",
  "variations": [
    {
      "id": "granary-1",
      "baseId": "granary",
      "type": "building",
      "name": "Granary",
      "nameCN": "谷仓",
      "pbgid": 156481,
      "attribName": "building_dynasty_granary_control_chi",
      "age": 1,
      "civs": [
        "ch"
      ],
      "description": "Villagers can drop off Food at this building. Improves the Farm gather rate of nearby Villagers by +10% (stacks with other Granaries). Generates tax each time a resource is dropped off.",
      "descriptionCN": "村民可将食物存放于这个建筑。使附近村民的农田采集速率 +10% (可与其他谷仓叠加)。每次存放资源都会产生税。",
      "classes": [
        "building",
        "economy_building",
        "granary",
        "gristmill",
        "land_food_deposit_4_by_4",
        "mill",
        "resource_drop_off",
        "siegeable"
      ],
      "displayClasses": [
        "Economy Building"
      ],
      "displayClassesCN": [
        "经济建筑"
      ],
      "unique": true,
      "costs": {
        "food": 0,
        "wood": 150,
        "stone": 0,
        "gold": 0,
        "vizier": 0,
        "oliveoil": 0,
        "total": 150,
        "popcap": 0,
        "time": 18
      },
      "producedBy": [
        "villager"
      ],
      "icon": "https://data.aoe4world.com/images/buildings/granary-1.png",
      "hitpoints": 1500,
      "weapons": [],
      "armor": [
        {
          "type": "ranged",
          "value": 50
        }
      ],
      "sight": {
        "inner_height": 8,
        "inner_radius": 10,
        "outer_height": -6,
        "outer_radius": 15,
        "base": 12.857142857142858,
        "line": 15,
        "height": 8
      },
      "influences": [
        "Buildings generate +100% tax while within the influence of the Imperial Academy."
      ],
      "influencesCN": [
        "建筑在受到翰林院的影响时产生的税 +100%。"
      ]
    },
    {
      "id": "granary-1",
      "baseId": "granary",
      "type": "building",
      "name": "Granary",
      "nameCN": "谷仓",
      "pbgid": 7869339,
      "attribName": "building_dynasty_granary_control_chi_ha_01",
      "age": 1,
      "civs": [
        "zx"
      ],
      "description": "Villagers can drop off Food at this building. Improves the Farm gather rate of nearby Villagers by +10% (stacks with other Granaries). Generates tax each time a resource is dropped off.",
      "descriptionCN": "村民可将食物存放于这个建筑。使附近村民的农田采集速率 +10% (可与其他谷仓叠加)。每次存放资源都会产生税。",
      "classes": [
        "building",
        "economy_building",
        "granary",
        "gristmill",
        "land_food_deposit_4_by_4",
        "mill",
        "resource_drop_off",
        "siegeable"
      ],
      "displayClasses": [
        "Economy Building"
      ],
      "displayClassesCN": [
        "经济建筑"
      ],
      "unique": true,
      "costs": {
        "food": 0,
        "wood": 150,
        "stone": 0,
        "gold": 0,
        "vizier": 0,
        "oliveoil": 0,
        "total": 150,
        "popcap": 0,
        "time": 35
      },
      "producedBy": [
        "villager"
      ],
      "icon": "https://data.aoe4world.com/images/buildings/granary-1.png",
      "hitpoints": 1500,
      "weapons": [],
      "armor": [
        {
          "type": "ranged",
          "value": 50
        }
      ],
      "sight": {
        "inner_height": 8,
        "inner_radius": 10,
        "outer_height": -6,
        "outer_radius": 15,
        "base": 12.857142857142858,
        "line": 15,
        "height": 8
      },
      "influences": [],
      "influencesCN": []
    }
  ]
}